{
  "productos": [
    {
      "id": 1,
      "name": "Laptop",
      "price": 2500000,
      "description": "Laptop ASUS VivoBook"
    },
    {
      "id": 2,
      "name": "Mouse Gamer",
      "price": 2500000,
      "description": "Mouse Gamer Razer"
    },
    {
      "id": 3,
      "name": "Teclado Gamer",
      "price": 2500000,
      "description": "Teclado Gamer Razer"
    },
    {
      "id": 4,
      "name": "Gamepad Anime",
      "price": 50000,
      "description": "TGamepad Anime Naruto"
    },
    {
      "name": "sadsad",
      "price": "dsadsad",
      "description": "dsadsa",
      "id": 5
    }
  ]
}